README.txt
setup.py
mrcli/__init__.py
mrcli/cmdline.py
mrcli/mrcli.py
mrcli.egg-info/PKG-INFO
mrcli.egg-info/SOURCES.txt
mrcli.egg-info/dependency_links.txt
mrcli.egg-info/entry_points.txt
mrcli.egg-info/requires.txt
mrcli.egg-info/top_level.txt
mrcli.egg-info/zip-safe