Metadata-Version: 1.0
Name: mrcli
Version: 0.3
Summary: Mister CLI: A multi-router network command-line interface.
Home-page: http://code.google.com/p/mr-cli/
Author: Andrew Fort
Author-email: notch-dev@googlegroups.com
License: http://www.apache.org/licenses/LICENSE-2.0
Platform: UNKNOWN
Classifier: Development Status :: 2 - Pre-Alpha
Classifier: Environment :: Console
Classifier: Intended Audience :: System Administrators
Classifier: License :: OSI Approved :: Apache Software License
Classifier: Operating System :: POSIX
Classifier: Programming Language :: Python :: 2.6
Classifier: Topic :: System :: Networking :: Monitoring
Classifier: Topic :: System :: Systems Administration
